juspy/__init__.py
juspy/greet.py
juspy/plot.py
juspy-0.0.1.dist-info/LICENSE
juspy-0.0.1.dist-info/METADATA
juspy-0.0.1.dist-info/WHEEL
juspy-0.0.1.dist-info/top_level.txt
juspy-0.0.1.dist-info/RECORD
