Metadata-Version: 2.1
Name: juspy
Version: 0.0.1
Summary: An EDA and modellling assist library
Home-page: https://github.com/juspreet51/juspy
Author: Jaspreet Singh
Author-email: contact@juspreet51.in
License: UNKNOWN
Download-URL: https://github.com/juspreet51/juspy
Project-URL: Bug Tracker, https://github.com/juspreet51/juspy
Project-URL: Documentation, https://github.com/juspreet51/juspy
Project-URL: Source Code, https://github.com/juspreet51/juspy
Platform: UNKNOWN
Classifier: Programming Language :: Python :: 3
Classifier: License :: OSI Approved :: MIT License
Classifier: Operating System :: OS Independent
Requires-Python: >=3.6
License-File: LICENSE
Requires-Dist: seaborn (>=0.11.2)
